llm2dict/__init__.py
llm2dict/api.py
llm2dict/execute.py
llm2dict/llm2dict.py
llm2dict/prompt.py
llm2dict/validate.py
llm2dict-0.0.4.dist-info/LICENSE
llm2dict-0.0.4.dist-info/METADATA
llm2dict-0.0.4.dist-info/WHEEL
llm2dict-0.0.4.dist-info/top_level.txt
llm2dict-0.0.4.dist-info/RECORD
