Metadata-Version: 2.2
Name: llm2dict
Version: 0.0.4
Summary: Enable large language models to output structured data.
Home-page: https://github.com/NNNINNN/llm2dict
Author: NNNINNN
Author-email: jianningwork@outlook.com
Classifier: Programming Language :: Python :: 3
Classifier: License :: OSI Approved :: MIT License
Classifier: Operating System :: OS Independent
Requires-Python: >=3.6
License-File: LICENSE
Requires-Dist: requests
Dynamic: author
Dynamic: author-email
Dynamic: classifier
Dynamic: description
Dynamic: description-content-type
Dynamic: home-page
Dynamic: requires-dist
Dynamic: requires-python
Dynamic: summary
